opentelemetry/instrumentation/openai/__init__.py
opentelemetry/instrumentation/openai/version.py
opentelemetry_instrumentation_openai_v2-0.3.4.dist-info/METADATA
opentelemetry_instrumentation_openai_v2-0.3.4.dist-info/WHEEL
opentelemetry_instrumentation_openai_v2-0.3.4.dist-info/RECORD
