Metadata-Version: 2.1
Name: opentelemetry-instrumentation-openai-v2
Version: 0.3.4
Summary: OpenTelemetry OpenAI instrumentation
License: Apache-2.0
Author: Gal Kleinman
Author-email: gal@traceloop.com
Requires-Python: >=3.8.1,<4
Classifier: License :: OSI Approved :: Apache Software License
Classifier: Programming Language :: Python :: 3
Classifier: Programming Language :: Python :: 3.9
Classifier: Programming Language :: Python :: 3.10
Classifier: Programming Language :: Python :: 3.11
Requires-Dist: opentelemetry-api (>=1.21.0,<2.0.0)
Requires-Dist: opentelemetry-instrumentation (>=0.42b0,<0.43)
Requires-Dist: opentelemetry-semantic-conventions-ai-v2 (>=0.0.7,<0.0.8)
